README.md
setup.cfg
setup.py
dbops_py_utilities/__init__.py
dbops_py_utilities.egg-info/PKG-INFO
dbops_py_utilities.egg-info/SOURCES.txt
dbops_py_utilities.egg-info/dependency_links.txt
dbops_py_utilities.egg-info/requires.txt
dbops_py_utilities.egg-info/top_level.txt
dbops_py_utilities/webapps/__init__.py
dbops_py_utilities/webapps/django/__init__.py
dbops_py_utilities/webapps/django/middleware/__init__.py
dbops_py_utilities/webapps/django/middleware/statsd_exporter.py