Metadata-Version: 1.1
Name: dbops-py-utilities
Version: 0.5
Summary: python utilites for DevOps/SRE
Home-page: UNKNOWN
Author: Santosh Kumar
Author-email: skumar21886@gmail.com
License: UNKNOWN
Download-URL: https://github.com/Demandbase/dbops-py-utilities/archive/0.1.tar.gz
Keywords: DevOps
Platform: UNKNOWN
Classifier: Development Status :: 3 - Alpha
Classifier: Intended Audience :: Developers
Classifier: Topic :: Software Development :: Build Tools
Classifier: Programming Language :: Python :: 3.6
